unbekanntekiste/__init__.py
unbekanntekiste/assumption.py
unbekanntekiste/figure.py
unbekanntekiste/message.py
unbekanntekiste-1.0.3.dist-info/METADATA
unbekanntekiste-1.0.3.dist-info/WHEEL
unbekanntekiste-1.0.3.dist-info/top_level.txt
unbekanntekiste-1.0.3.dist-info/RECORD
