Metadata-Version: 2.1
Name: unbekanntekiste
Version: 1.0.3
Summary: bounding polygons matrixlizer captured by google cloud platform vision api
Home-page: UNKNOWN
License: MIT
Platform: UNKNOWN
Classifier: Programming Language :: Python :: 3
Classifier: License :: OSI Approved :: MIT License
Classifier: Operating System :: OS Independent
